{"rows":[{"adcode":130302,"lng":119.596224,"lat":39.943458,"name":"海港区","level":"district","parent":130300},{"adcode":130303,"lng":119.753591,"lat":39.998023,"name":"山海关区","level":"district","parent":130300},{"adcode":130304,"lng":119.486286,"lat":39.825121,"name":"北戴河区","level":"district","parent":130300},{"adcode":130306,"lng":119.240651,"lat":39.887053,"name":"抚宁区","level":"district","parent":130300},{"adcode":130321,"lng":118.954555,"lat":40.406023,"name":"青龙满族自治县","level":"district","parent":130300},{"adcode":130322,"lng":119.164541,"lat":39.709729,"name":"昌黎县","level":"district","parent":130300},{"adcode":130324,"lng":118.881809,"lat":39.891639,"name":"卢龙县","level":"district","parent":130300}],"total":7}