{"rows":[{"adcode":211002,"lng":123.172611,"lat":41.26745,"name":"白塔区","level":"district","parent":211000},{"adcode":211003,"lng":123.188227,"lat":41.266765,"name":"文圣区","level":"district","parent":211000},{"adcode":211004,"lng":123.200461,"lat":41.205747,"name":"宏伟区","level":"district","parent":211000},{"adcode":211005,"lng":123.431633,"lat":41.157831,"name":"弓长岭区","level":"district","parent":211000},{"adcode":211011,"lng":123.185336,"lat":41.251682,"name":"太子河区","level":"district","parent":211000},{"adcode":211021,"lng":123.079674,"lat":41.216479,"name":"辽阳县","level":"district","parent":211000},{"adcode":211081,"lng":123.325864,"lat":41.427836,"name":"灯塔市","level":"district","parent":211000}],"total":7}