{"rows":[{"adcode":340302,"lng":117.382312,"lat":32.950452,"name":"龙子湖区","level":"district","parent":340300},{"adcode":340303,"lng":117.355789,"lat":32.938066,"name":"蚌山区","level":"district","parent":340300},{"adcode":340304,"lng":117.35259,"lat":32.931933,"name":"禹会区","level":"district","parent":340300},{"adcode":340311,"lng":117.34709,"lat":32.963147,"name":"淮上区","level":"district","parent":340300},{"adcode":340321,"lng":117.200171,"lat":32.956934,"name":"怀远县","level":"district","parent":340300},{"adcode":340322,"lng":117.888809,"lat":33.146202,"name":"五河县","level":"district","parent":340300},{"adcode":340323,"lng":117.315962,"lat":33.318679,"name":"固镇县","level":"district","parent":340300}],"total":7}