{"rows":[{"adcode":350602,"lng":117.656461,"lat":24.509955,"name":"芗城区","level":"district","parent":350600},{"adcode":350603,"lng":117.671387,"lat":24.515656,"name":"龙文区","level":"district","parent":350600},{"adcode":350622,"lng":117.340946,"lat":23.950486,"name":"云霄县","level":"district","parent":350600},{"adcode":350623,"lng":117.614023,"lat":24.117907,"name":"漳浦县","level":"district","parent":350600},{"adcode":350624,"lng":117.176083,"lat":23.710834,"name":"诏安县","level":"district","parent":350600},{"adcode":350625,"lng":117.755913,"lat":24.621475,"name":"长泰县","level":"district","parent":350600},{"adcode":350626,"lng":117.427679,"lat":23.702845,"name":"东山县","level":"district","parent":350600},{"adcode":350627,"lng":117.365462,"lat":24.516425,"name":"南靖县","level":"district","parent":350600},{"adcode":350628,"lng":117.313549,"lat":24.366158,"name":"平和县","level":"district","parent":350600},{"adcode":350629,"lng":117.53631,"lat":25.001416,"name":"华安县","level":"district","parent":350600},{"adcode":350681,"lng":117.817292,"lat":24.445341,"name":"龙海市","level":"district","parent":350600}],"total":11}