{"rows":[{"adcode":360102,"lng":115.889675,"lat":28.682988,"name":"东湖区","level":"district","parent":360100},{"adcode":360103,"lng":115.91065,"lat":28.662901,"name":"西湖区","level":"district","parent":360100},{"adcode":360104,"lng":115.907292,"lat":28.635724,"name":"青云谱区","level":"district","parent":360100},{"adcode":360105,"lng":115.731324,"lat":28.714803,"name":"湾里区","level":"district","parent":360100},{"adcode":360111,"lng":115.949044,"lat":28.689292,"name":"青山湖区","level":"district","parent":360100},{"adcode":360112,"lng":115.820806,"lat":28.690788,"name":"新建区","level":"district","parent":360100},{"adcode":360121,"lng":115.942465,"lat":28.543781,"name":"南昌县","level":"district","parent":360100},{"adcode":360123,"lng":115.553109,"lat":28.841334,"name":"安义县","level":"district","parent":360100},{"adcode":360124,"lng":116.267671,"lat":28.365681,"name":"进贤县","level":"district","parent":360100}],"total":9}