{"rows":[{"adcode":440303,"lng":114.123885,"lat":22.555341,"name":"罗湖区","level":"district","parent":440300},{"adcode":440304,"lng":114.05096,"lat":22.541009,"name":"福田区","level":"district","parent":440300},{"adcode":440305,"lng":113.92943,"lat":22.531221,"name":"南山区","level":"district","parent":440300},{"adcode":440306,"lng":113.828671,"lat":22.754741,"name":"宝安区","level":"district","parent":440300},{"adcode":440307,"lng":114.251372,"lat":22.721511,"name":"龙岗区","level":"district","parent":440300},{"adcode":440308,"lng":114.235366,"lat":22.555069,"name":"盐田区","level":"district","parent":440300},{"adcode":440309,"lng":114.044346,"lat":22.691963,"name":"龙华区","level":"district","parent":440300},{"adcode":440310,"lng":114.338441,"lat":22.69423,"name":"坪山区","level":"district","parent":440300},{"adcode":440311,"lng":113.935895,"lat":22.748816,"name":"光明区","level":"district","parent":440300}],"total":9}