{"rows":[{"adcode":520302,"lng":106.943784,"lat":27.694395,"name":"红花岗区","level":"district","parent":520300},{"adcode":520303,"lng":106.937265,"lat":27.706626,"name":"汇川区","level":"district","parent":520300},{"adcode":520304,"lng":106.831668,"lat":27.535288,"name":"播州区","level":"district","parent":520300},{"adcode":520322,"lng":106.826591,"lat":28.131559,"name":"桐梓县","level":"district","parent":520300},{"adcode":520323,"lng":107.191024,"lat":27.951342,"name":"绥阳县","level":"district","parent":520300},{"adcode":520324,"lng":107.441872,"lat":28.550337,"name":"正安县","level":"district","parent":520300},{"adcode":520325,"lng":107.605342,"lat":28.880088,"name":"道真仡佬族苗族自治县","level":"district","parent":520300},{"adcode":520326,"lng":107.887857,"lat":28.521567,"name":"务川仡佬族苗族自治县","level":"district","parent":520300},{"adcode":520327,"lng":107.722021,"lat":27.960858,"name":"凤冈县","level":"district","parent":520300},{"adcode":520328,"lng":107.485723,"lat":27.765839,"name":"湄潭县","level":"district","parent":520300},{"adcode":520329,"lng":107.892566,"lat":27.221552,"name":"余庆县","level":"district","parent":520300},{"adcode":520330,"lng":106.200954,"lat":28.327826,"name":"习水县","level":"district","parent":520300},{"adcode":520381,"lng":105.698116,"lat":28.587057,"name":"赤水市","level":"district","parent":520300},{"adcode":520382,"lng":106.412476,"lat":27.803377,"name":"仁怀市","level":"district","parent":520300}],"total":14}