{"rows":[{"adcode":520402,"lng":105.946169,"lat":26.248323,"name":"西秀区","level":"district","parent":520400},{"adcode":520403,"lng":106.259942,"lat":26.40608,"name":"平坝区","level":"district","parent":520400},{"adcode":520422,"lng":105.745609,"lat":26.305794,"name":"普定县","level":"district","parent":520400},{"adcode":520423,"lng":105.768656,"lat":26.056096,"name":"镇宁布依族苗族自治县","level":"district","parent":520400},{"adcode":520424,"lng":105.618454,"lat":25.944248,"name":"关岭布依族苗族自治县","level":"district","parent":520400},{"adcode":520425,"lng":106.084515,"lat":25.751567,"name":"紫云苗族布依族自治县","level":"district","parent":520400}],"total":6}