{"rows":[{"adcode":621102,"lng":104.62577,"lat":35.579764,"name":"安定区","level":"district","parent":621100},{"adcode":621121,"lng":105.250102,"lat":35.208922,"name":"通渭县","level":"district","parent":621100},{"adcode":621122,"lng":104.637554,"lat":35.003409,"name":"陇西县","level":"district","parent":621100},{"adcode":621123,"lng":104.211742,"lat":35.133023,"name":"渭源县","level":"district","parent":621100},{"adcode":621124,"lng":103.862186,"lat":35.376233,"name":"临洮县","level":"district","parent":621100},{"adcode":621125,"lng":104.466756,"lat":34.848642,"name":"漳县","level":"district","parent":621100},{"adcode":621126,"lng":104.039882,"lat":34.439105,"name":"岷县","level":"district","parent":621100}],"total":7}